{"name":"build-javascript","namedChunkGroups":{"app":{"name":"app","assets":[{"name":"webpack-runtime-afef85092ef289af03f3.js","size":3772},{"name":"framework-5afa7227ef707c09334a.js","size":140301},{"name":"styles.501f32d012ee44c8ed05.css","size":83308},{"name":"app-b755d4ee048a4c94f1e4.js","size":81875}],"filteredAssets":0,"assetsSize":309256,"filteredAuxiliaryAssets":3,"auxiliaryAssetsSize":672176},"component---src-pages-404-jsx":{"name":"component---src-pages-404-jsx","assets":[{"name":"component---src-pages-404-jsx-6fb6726e5bd3826de2e7.js","size":476}],"filteredAssets":0,"assetsSize":476,"filteredAuxiliaryAssets":1,"auxiliaryAssetsSize":734},"component---src-templates-docs-jsx":{"name":"component---src-templates-docs-jsx","assets":[{"name":"component---src-templates-docs-jsx-f9377174dff5bca9c275.js","size":45445}],"filteredAssets":0,"assetsSize":45445,"filteredAuxiliaryAssets":1,"auxiliaryAssetsSize":179350}},"assetsByChunkName":{"app":["webpack-runtime-afef85092ef289af03f3.js","framework-5afa7227ef707c09334a.js","styles.501f32d012ee44c8ed05.css","app-b755d4ee048a4c94f1e4.js"],"component---src-pages-404-jsx":["component---src-pages-404-jsx-6fb6726e5bd3826de2e7.js"],"component---src-templates-docs-jsx":["component---src-templates-docs-jsx-f9377174dff5bca9c275.js"]},"childAssetsByChunkName":{}}